pf/__init__.py
pf-0.1.1.dist-info/WHEEL
pf-0.1.1.dist-info/METADATA
pf-0.1.1.dist-info/RECORD
